LICENSE
MANIFEST.in
README.rst
setup.py
WTFMongoengine.egg-info/PKG-INFO
WTFMongoengine.egg-info/SOURCES.txt
WTFMongoengine.egg-info/dependency_links.txt
WTFMongoengine.egg-info/requires.txt
WTFMongoengine.egg-info/top_level.txt
wtfmongoengine/__init__.py
wtfmongoengine/forms.py