Metadata-Version: 1.0
Name: WTFMongoengine
Version: 0.1.2
Summary: WTForms for Mongoengine documents
Home-page: http://github.com/brocaar/wtfmongoengine
Author: Orne Brocaar
Author-email: info@brocaar.com
License: BSD
Platform: UNKNOWN
Classifier: Development Status :: 4 - Beta
Classifier: Environment :: Web Environment
Classifier: Intended Audience :: Developers
Classifier: License :: OSI Approved :: BSD License
Classifier: Operating System :: OS Independent
Classifier: Programming Language :: Python
Classifier: Topic :: Internet :: WWW/HTTP :: Dynamic Content
Classifier: Topic :: Software Development :: Libraries :: Python Modules
